StructNoSQL/__init__.py
StructNoSQL/exceptions.py
StructNoSQL/fields.py
StructNoSQL/models.py
StructNoSQL/practical_logger.py
StructNoSQL/query.py
StructNoSQL/validator.py
StructNoSQL/clients_middlewares/__init__.py
StructNoSQL/clients_middlewares/dynamodb/__init__.py
StructNoSQL/clients_middlewares/dynamodb/dynamodb_basic_table.py
StructNoSQL/clients_middlewares/dynamodb/dynamodb_caching_table.py
StructNoSQL/clients_middlewares/dynamodb/dynamodb_low_level_table_operations.py
StructNoSQL/clients_middlewares/dynamodb/dynamodb_table_connectors.py
StructNoSQL/clients_middlewares/dynamodb/backend/__init__.py
StructNoSQL/clients_middlewares/dynamodb/backend/dynamodb_core.py
StructNoSQL/clients_middlewares/dynamodb/backend/dynamodb_utils.py
StructNoSQL/clients_middlewares/dynamodb/backend/models.py
StructNoSQL/clients_middlewares/external_dynamodb_api/__init__.py
StructNoSQL/clients_middlewares/external_dynamodb_api/external_dynamodb_api_basic_table.py
StructNoSQL/clients_middlewares/external_dynamodb_api/external_dynamodb_api_caching_table.py
StructNoSQL/clients_middlewares/external_dynamodb_api/external_dynamodb_api_table_connectors.py
StructNoSQL/servers_middlewares/__init__.py
StructNoSQL/servers_middlewares/external_dynamodb_api/__init__.py
StructNoSQL/servers_middlewares/external_dynamodb_api/api_executor.py
StructNoSQL/servers_middlewares/external_dynamodb_api/api_executor_handlers.py
StructNoSQL/servers_middlewares/external_dynamodb_api/low_level_table_client.py
StructNoSQL/servers_middlewares/external_dynamodb_api/models.py
StructNoSQL/servers_middlewares/external_dynamodb_api/parser.py
StructNoSQL/tables/__init__.py
StructNoSQL/tables/base_basic_table.py
StructNoSQL/tables/base_caching_table.py
StructNoSQL/tables/base_table.py
StructNoSQL/tables/shared_table_behaviors.py
StructNoSQL/utils/__init__.py
StructNoSQL/utils/data_processing.py
StructNoSQL/utils/decimals.py
StructNoSQL/utils/misc_fields_items.py
StructNoSQL/utils/objects.py
StructNoSQL-2.6.7.dist-info/LICENSE
StructNoSQL-2.6.7.dist-info/METADATA
StructNoSQL-2.6.7.dist-info/WHEEL
StructNoSQL-2.6.7.dist-info/top_level.txt
StructNoSQL-2.6.7.dist-info/RECORD
